[
  {
    "name": "Son Goku",
    "value": 5000000,
    "gender": "Hombre",
    "source": "Dragon Ball",
    "keyword": "son_goku"
  },
  {
    "name": "Gojo Satoru",
    "value": 4800000,
    "gender": "Hombre",
    "source": "Jujutsu Kaisen",
    "keyword": "gojo_satoru"
  },
  {
    "name": "Ryomen Sukuna",
    "value": 4700000,
    "gender": "Hombre",
    "source": "Jujutsu Kaisen",
    "keyword": "ryoumen_sukuna_(jujutsu_kaisen)"
  },
  {
    "name": "Saitama",
    "value": 4500000,
    "gender": "Hombre",
    "source": "One Punch Man",
    "keyword": "saitama_(one_punch_man)"
  },
  {
    "name": "Monkey D. Luffy",
    "value": 4200000,
    "gender": "Hombre",
    "source": "One Piece",
    "keyword": "monkey_d_luffy"
  },
  {
    "name": "Uzumaki Naruto",
    "value": 4000000,
    "gender": "Hombre",
    "source": "Naruto",
    "keyword": "uzumaki_naruto"
  },
  {
    "name": "Ellen Joe",
    "value": 1330000,
    "gender": "Mujer",
    "source": "Zenless Zone Zero",
    "keyword": "ellen_joe"
  },
  {
    "name": "Acheron",
    "value": 3750000,
    "gender": "Mujer",
    "source": "Honkai: Star Rail",
    "keyword": "acheron_(honkai:_star_rail)"
  },
  {
    "name": "Raiden Shogun",
    "value": 3700000,
    "gender": "Mujer",
    "source": "Genshin Impact",
    "keyword": "raiden_shogun"
  },
  {
    "name": "Makima",
    "value": 3600000,
    "gender": "Mujer",
    "source": "Chainsaw Man",
    "keyword": "makima"
  },
  {
    "name": "Frieren",
    "value": 3500000,
    "gender": "Mujer",
    "source": "Sousou no Frieren",
    "keyword": "frieren"
  },
  {
    "name": "Hu Tao",
    "value": 3400000,
    "gender": "Mujer",
    "source": "Genshin Impact",
    "keyword": "hu_tao"
  },
  {
    "name": "Zoro Roronoa",
    "value": 3300000,
    "gender": "Hombre",
    "source": "One Piece",
    "keyword": "zoro_roronoa"
  },
  {
    "name": "Yuta Okkotsu",
    "value": 3200000,
    "gender": "Hombre",
    "source": "Jujutsu Kaisen",
    "keyword": "okkotsu_yuuta"
  },
  {
    "name": "Kafka",
    "value": 3100000,
    "gender": "Mujer",
    "source": "Honkai: Star Rail",
    "keyword": "kafka_(honkai:_star_rail)"
  },
  {
    "name": "Shadow (Cid Kagenou)",
    "value": 3050000,
    "gender": "Hombre",
    "source": "Kage no Jitsuryokusha",
    "keyword": "cid_kagenou"
  },
  {
    "name": "Rimuru Tempest",
    "value": 3000000,
    "gender": "Desconocido",
    "source": "Tensei Shitara Slime",
    "keyword": "rimuru_tempest"
  },
  {
    "name": "Yor Forger",
    "value": 2900000,
    "gender": "Mujer",
    "source": "Spy x Family",
    "keyword": "yor_forger"
  },
  {
    "name": "Tokisaki Kurumi",
    "value": 2850000,
    "gender": "Mujer",
    "source": "Date A Live",
    "keyword": "tokisaki_kurumi"
  },
  {
    "name": "Kitagawa Marin",
    "value": 2800000,
    "gender": "Mujer",
    "source": "Sono Bisque Doll",
    "keyword": "kitagawa_marin"
  },
  {
    "name": "Firefly",
    "value": 2750000,
    "gender": "Mujer",
    "source": "Honkai: Star Rail",
    "keyword": "firefly_(honkai:_star_rail)"
  },
  {
    "name": "Furina",
    "value": 2700000,
    "gender": "Mujer",
    "source": "Genshin Impact",
    "keyword": "furina_(genshin_impact)"
  },
  {
    "name": "Hoshino Ai",
    "value": 2600000,
    "gender": "Mujer",
    "source": "Oshi no Ko",
    "keyword": "hoshino_ai"
  },
  {
    "name": "Rem",
    "value": 2500000,
    "gender": "Mujer",
    "source": "Re:Zero",
    "keyword": "rem_(re:zero)"
  },
  {
    "name": "Emilia",
    "value": 2400000,
    "gender": "Mujer",
    "source": "Re:Zero",
    "keyword": "emilia_(re:zero)"
  },
  {
    "name": "Hoshimi Miyabi",
    "value": 805000,
    "gender": "Mujer",
    "source": "Zenless Zone Zero",
    "keyword": "hoshimi_miyabi"
  },
  {
    "name": "Jane Doe",
    "value": 787500,
    "gender": "Mujer",
    "source": "Zenless Zone Zero",
    "keyword": "jane_doe_(zenless_zone_zero)"
  },
  {
    "name": "Zhu Yuan",
    "value": 770000,
    "gender": "Mujer",
    "source": "Zenless Zone Zero",
    "keyword": "zhu_yuan"
  },
  {
    "name": "2B",
    "value": 2150000,
    "gender": "Mujer",
    "source": "NieR:Automata",
    "keyword": "2b_(nier:automata)"
  },
  {
    "name": "Zero Two",
    "value": 2100000,
    "gender": "Mujer",
    "source": "Darling in the FranXX",
    "keyword": "zero_two_(darling_in_the_franxx)"
  },
  {
    "name": "Albedo",
    "value": 2050000,
    "gender": "Mujer",
    "source": "Overlord",
    "keyword": "albedo_(overlord)"
  },
  {
    "name": "Megumin",
    "value": 2000000,
    "gender": "Mujer",
    "source": "Konosuba",
    "keyword": "megumin"
  },
  {
    "name": "Power",
    "value": 1900000,
    "gender": "Mujer",
    "source": "Chainsaw Man",
    "keyword": "power_(chainsaw_man)"
  },
  {
    "name": "Denji",
    "value": 1800000,
    "gender": "Hombre",
    "source": "Chainsaw Man",
    "keyword": "denji"
  },
  {
    "name": "Yuji Itadori",
    "value": 1750000,
    "gender": "Hombre",
    "source": "Jujutsu Kaisen",
    "keyword": "itadori_yuuji"
  },
  {
    "name": "Mahoraga",
    "value": 1700000,
    "gender": "Hombre",
    "source": "Jujutsu Kaisen",
    "keyword": "mahoraga_(jujutsu_kaisen)"
  },
  {
    "name": "Yamato",
    "value": 1650000,
    "gender": "Mujer",
    "source": "One Piece",
    "keyword": "yamato_(one_piece)"
  },
  {
    "name": "Gawr Gura",
    "value": 640000,
    "gender": "Mujer",
    "source": "Hololive",
    "keyword": "gawr_gura"
  },
  {
    "name": "Hitori Gotou",
    "value": 1500000,
    "gender": "Mujer",
    "source": "Bocchi the Rock",
    "keyword": "bocchi"
  },
  {
    "name": "Kamado Nezuko",
    "value": 870000,
    "gender": "Mujer",
    "source": "Kimetsu no Yaiba",
    "keyword": "kamado_nezuko"
  },
  {
    "name": "Shinobu Kocho",
    "value": 840000,
    "gender": "Mujer",
    "source": "Kimetsu no Yaiba",
    "keyword": "kochou_shinobu"
  },
  {
    "name": "Kanroji Mitsuri",
    "value": 810000,
    "gender": "Mujer",
    "source": "Kimetsu no Yaiba",
    "keyword": "kanroji_mitsuri"
  },
  {
    "name": "Shinomiya Kaguya",
    "value": 780000,
    "gender": "Mujer",
    "source": "Kaguya-sama",
    "keyword": "shinomiya_kaguya"
  },
  {
    "name": "Nakano Miku",
    "value": 687500,
    "gender": "Mujer",
    "source": "Gotoubun no Hanayome",
    "keyword": "nakano_miku"
  },
  {
    "name": "Nakano Nino",
    "value": 660000,
    "gender": "Mujer",
    "source": "Gotoubun no Hanayome",
    "keyword": "nakano_nino"
  },
  {
    "name": "Mao Mao",
    "value": 600000,
    "gender": "Mujer",
    "source": "Kusuriya no Hitorigoto",
    "keyword": "maomao_(kusuriya_no_hitorigoto)"
  },
  {
    "name": "Senko San",
    "value": 202500,
    "gender": "Mujer",
    "source": "Sewayaki Kitsune no Senko-san",
    "keyword": "senko_(sewayaki_kitsune_no_senko-san)"
  },
  {
    "name": "Amano Erika",
    "value": 212836,
    "gender": "Mujer",
    "source": "Kakkou no Iinazuke",
    "keyword": "amano_erika"
  },
  {
    "name": "Segawa Hiro",
    "value": 208332,
    "gender": "Mujer",
    "source": "Kakkou no Iinazuke",
    "keyword": "segawa_hiro"
  },
  {
    "name": "Umino Sachi",
    "value": 368712,
    "gender": "Mujer",
    "source": "Kakkou no Iinazuke",
    "keyword": "umino_sachi_(kakkou_no_iinazuke)"
  },
  {
    "name": "Umino Nagi",
    "value": 162801,
    "gender": "Hombre",
    "source": "Kakkou no Iinazuke",
    "keyword": "umino_nagi"
  },
  {
    "name": "Jinshi",
    "value": 350000,
    "gender": "Hombre",
    "source": "Kusuriya no Hitorigoto",
    "keyword": "jinshi_(kusuriya_no_hitorigoto)"
  },
  {
    "name": "Xiaolan",
    "value": 181480,
    "gender": "Mujer",
    "source": "Kusuriya no Hitorigoto",
    "keyword": "xiaolan_(kusuriya_no_hitorigoto)"
  },
  {
    "name": "Lihua",
    "value": 135980,
    "gender": "Mujer",
    "source": "Kusuriya no Hitorigoto",
    "keyword": "lihua_(kusuriya_no_hitorigoto)"
  },
  {
    "name": "Loulan",
    "value": 91830,
    "gender": "Mujer",
    "source": "Kusuriya no Hitorigoto",
    "keyword": "loulan_(kusuriya_no_hitorigoto)"
  },
  {
    "name": "Gyokuyou",
    "value": 130930,
    "gender": "Mujer",
    "source": "Kusuriya no Hitorigoto",
    "keyword": "gyokuyou_(kusuriya_no_hitorigoto)"
  },
  {
    "name": "Pairin",
    "value": 80000,
    "gender": "Mujer",
    "source": "Kusuriya no Hitorigoto",
    "keyword": "pairin_(kusuriya_no_hitorigoto)"
  },
  {
    "name": "Meimei",
    "value": 130930,
    "gender": "Mujer",
    "source": "Kusuriya no Hitorigoto",
    "keyword": "meimei_(kusuriya_no_hitorigoto)"
  },
  {
    "name": "Lishu",
    "value": 80000,
    "gender": "Mujer",
    "source": "Kusuriya no Hitorigoto",
    "keyword": "lishu_(kusuriya_no_hitorigoto)"
  },
  {
    "name": "Rahan",
    "value": 134355,
    "gender": "Hombre",
    "source": "Kusuriya no Hitorigoto",
    "keyword": "rahan_(kusuriya_no_hitorigoto)"
  },
  {
    "name": "Gaoshun",
    "value": 80000,
    "gender": "Hombre",
    "source": "Kusuriya no Hitorigoto",
    "keyword": "gaoshun_(kusuriya_no_hitorigoto)"
  },
  {
    "name": "Ah-Dou",
    "value": 80000,
    "gender": "Mujer",
    "source": "Kusuriya no Hitorigoto",
    "keyword": "ah-duo_(kusuriya_no_hitorigoto)"
  },
  {
    "name": "Koshi Torako",
    "value": 60000,
    "gender": "Mujer",
    "source": "Shikanoko Nokonoko Koshitantan",
    "keyword": "koshi_torako"
  },
  {
    "name": "Nekoyamada Neko",
    "value": 162882,
    "gender": "Mujer",
    "source": "Shikanoko Nokonoko Koshitantan",
    "keyword": "nekoyamada_neko"
  },
  {
    "name": "Shikanoko Noko",
    "value": 60000,
    "gender": "Mujer",
    "source": "Shikanoko Nokonoko Koshitantan",
    "keyword": "shikanoko_noko"
  },
  {
    "name": "Bashame Meme",
    "value": 118782,
    "gender": "Mujer",
    "source": "Shikanoko Nokonoko Koshitantan",
    "keyword": "bashame_meme"
  },
  {
    "name": "Araga Kiwi",
    "value": 105184,
    "gender": "Mujer",
    "source": "Mahou Shoujo ni Akogarate",
    "keyword": "araga_kiwi"
  },
  {
    "name": "Hiiragi Utena",
    "value": 60000,
    "gender": "Mujer",
    "source": "Mahou Shoujo ni Akogarate",
    "keyword": "hiiragi_utena"
  },
  {
    "name": "Fujiwara Chika",
    "value": 300000,
    "gender": "Mujer",
    "source": "Kaguya-sama",
    "keyword": "fujiwara_chika"
  },
  {
    "name": "Iino Miko",
    "value": 165834,
    "gender": "Mujer",
    "source": "Kaguya-sama",
    "keyword": "iino_miko"
  },
  {
    "name": "Ishigami Yuu",
    "value": 412968,
    "gender": "Hombre",
    "source": "Kaguya-sama",
    "keyword": "ishigami_yuu"
  },
  {
    "name": "Shirogane Miyuki",
    "value": 400000,
    "gender": "Hombre",
    "source": "Kaguya-sama",
    "keyword": "shirogane_miyuki"
  },
  {
    "name": "Fujiwara Moeha",
    "value": 231756,
    "gender": "Mujer",
    "source": "Kaguya-sama",
    "keyword": "fujiwara_moeha"
  },
  {
    "name": "Shirogane Kei",
    "value": 283776,
    "gender": "Mujer",
    "source": "Kaguya-sama",
    "keyword": "shirogane_kei"
  },
  {
    "name": "Trigger",
    "value": 95053,
    "gender": "Mujer",
    "source": "Zenless Zone Zero",
    "keyword": "trigger_(zenless_zone_zero)"
  },
  {
    "name": "Tsukishiro Yanagi",
    "value": 130546,
    "gender": "Mujer",
    "source": "Zenless Zone Zero",
    "keyword": "tsukishiro_yanagi"
  },
  {
    "name": "Belle",
    "value": 130504,
    "gender": "Mujer",
    "source": "Zenless Zone Zero",
    "keyword": "belle_(zenless_zone_zero)"
  },
  {
    "name": "Burnice White",
    "value": 95889,
    "gender": "Mujer",
    "source": "Zenless Zone Zero",
    "keyword": "burnice_white"
  },
  {
    "name": "Anby Demara",
    "value": 95525,
    "gender": "Mujer",
    "source": "Zenless Zone Zero",
    "keyword": "anby_demara"
  },
  {
    "name": "Astra Yao",
    "value": 265429,
    "gender": "Mujer",
    "source": "Zenless Zone Zero",
    "keyword": "astra_yao"
  },
  {
    "name": "Evelyn Chevalier",
    "value": 99284,
    "gender": "Mujer",
    "source": "Zenless Zone Zero",
    "keyword": "evelyn_chevalier"
  },
  {
    "name": "Caesar King",
    "value": 98588,
    "gender": "Mujer",
    "source": "Zenless Zone Zero",
    "keyword": "caesar_king_(zenless_zone_zero)"
  },
  {
    "name": "Nekomiya Mana",
    "value": 130535,
    "gender": "Mujer",
    "source": "Zenless Zone Zero",
    "keyword": "nekomiya_mana"
  },
  {
    "name": "Ben Bigger",
    "value": 306239,
    "gender": "Hombre",
    "source": "Zenless Zone Zero",
    "keyword": "ben_bigger"
  },
  {
    "name": "Vivian Banshee",
    "value": 95539,
    "gender": "Mujer",
    "source": "Zenless Zone Zero",
    "keyword": "vivian_banshee"
  },
  {
    "name": "Qingyi",
    "value": 91686,
    "gender": "Mujer",
    "source": "Zenless Zone Zero",
    "keyword": "qingyi_(zenless_zone_zero)"
  },
  {
    "name": "Corin Wickes",
    "value": 130185,
    "gender": "Mujer",
    "source": "Zenless Zone Zero",
    "keyword": "corin_wickes"
  },
  {
    "name": "Nicole Demara",
    "value": 220353,
    "gender": "Mujer",
    "source": "Zenless Zone Zero",
    "keyword": "nicole_demara"
  },
  {
    "name": "Ju Fufu",
    "value": 80000,
    "gender": "Mujer",
    "source": "Zenless Zone Zero",
    "keyword": "ju_fufu"
  },
  {
    "name": "Pulchra Fellini",
    "value": 204288,
    "gender": "Mujer",
    "source": "Zenless Zone Zero",
    "keyword": "pulchra_fellini"
  },
  {
    "name": "Yi Xuan",
    "value": 102826,
    "gender": "Mujer",
    "source": "Zenless Zone Zero",
    "keyword": "yixuan_(zenless_zone_zero)"
  },
  {
    "name": "Venus",
    "value": 99288,
    "gender": "Mujer",
    "source": "Zenless Zone Zero",
    "keyword": "venus_(zenless_zone_zero)"
  },
  {
    "name": "Luciana De Montefio",
    "value": 95889,
    "gender": "Mujer",
    "source": "Zenless Zone Zero",
    "keyword": "luciana_de_montefio"
  },
  {
    "name": "Piper Wheel",
    "value": 130889,
    "gender": "Mujer",
    "source": "Zenless Zone Zero",
    "keyword": "piper_wheel"
  },
  {
    "name": "Lighter",
    "value": 165539,
    "gender": "Mujer",
    "source": "Zenless Zone Zero",
    "keyword": "lighter_(zenless_zone_zero)"
  },
  {
    "name": "Soldier 11",
    "value": 99316,
    "gender": "Mujer",
    "source": "Zenless Zone Zero",
    "keyword": "soldier_11_(zenless_zone_zero)"
  },
  {
    "name": "Sweety",
    "value": 133966,
    "gender": "Mujer",
    "source": "Zenless Zone Zero",
    "keyword": "sweety_(zenless_zone_zero)"
  },
  {
    "name": "Alexandrina Sebastiane",
    "value": 340543,
    "gender": "Mujer",
    "source": "Zenless Zone Zero",
    "keyword": "alexandrina_sebastiane"
  },
  {
    "name": "Soukaku",
    "value": 128890,
    "gender": "Mujer",
    "source": "Zenless Zone Zero",
    "keyword": "soukaku_(zenless_zone_zero)"
  },
  {
    "name": "Wise",
    "value": 255384,
    "gender": "Mujer",
    "source": "Zenless Zone Zero",
    "keyword": "wise_(zenless_zone_zero)"
  },
  {
    "name": "Von Lycaon",
    "value": 131523,
    "gender": "Hombre",
    "source": "Zenless Zone Zero",
    "keyword": "von_lycaon"
  },
  {
    "name": "Asaba Harumasa",
    "value": 299519,
    "gender": "Hombre",
    "source": "Zenless Zone Zero",
    "keyword": "asaba_harumasa"
  },
  {
    "name": "Billy Kid",
    "value": 130500,
    "gender": "Mujer",
    "source": "Zenless Zone Zero",
    "keyword": "billy_kid"
  },
  {
    "name": "Seth Lowell",
    "value": 95749,
    "gender": "Hombre",
    "source": "Zenless Zone Zero",
    "keyword": "seth_lowell"
  },
  {
    "name": "Koleda Belobog",
    "value": 130885,
    "gender": "Mujer",
    "source": "Zenless Zone Zero",
    "keyword": "koleda_belobog"
  },
  {
    "name": "Hugo Vlad",
    "value": 99288,
    "gender": "Hombre",
    "source": "Zenless Zone Zero",
    "keyword": "hugo_vlad"
  },
  {
    "name": "Coco",
    "value": 288319,
    "gender": "Mujer",
    "source": "Zenless Zone Zero",
    "keyword": "coco_(zenless_zone_zero)"
  },
  {
    "name": "Orchidea",
    "value": 258422,
    "gender": "Mujer",
    "source": "Zenless Zone Zero",
    "keyword": "orchidea_(zenless_zone_zero)"
  },
  {
    "name": "Alice Thymefield",
    "value": 95788,
    "gender": "Mujer",
    "source": "Zenless Zone Zero",
    "keyword": "alice_thymefield"
  },
  {
    "name": "Ukinami Yuzuha",
    "value": 162001,
    "gender": "Mujer",
    "source": "Zenless Zone Zero",
    "keyword": "ukinami_yuzuha"
  },
  {
    "name": "Twiggy",
    "value": 92351,
    "gender": "Mujer",
    "source": "Zenless Zone Zero",
    "keyword": "twiggy_(zenless_zone_zero)"
  },
  {
    "name": "Pan Yinhu",
    "value": 232354,
    "gender": "Mujer",
    "source": "Zenless Zone Zero",
    "keyword": "pan_yinhu"
  },
  {
    "name": "Pompey",
    "value": 80000,
    "gender": "Hombre",
    "source": "Zenless Zone Zero",
    "keyword": "pompey_(zenless_zone_zero)"
  },
  {
    "name": "Orpheus",
    "value": 257904,
    "gender": "Mujer",
    "source": "Zenless Zone Zero",
    "keyword": "orpheus_(zenless_zone_zero)"
  },
  {
    "name": "Rain",
    "value": 128400,
    "gender": "Mujer",
    "source": "Zenless Zone Zero",
    "keyword": "rain_(zenless_zone_zero)"
  },
  {
    "name": "Bangboo",
    "value": 207788,
    "gender": "Mujer",
    "source": "Zenless Zone Zero",
    "keyword": "bangboo_(zenless_zone_zero)"
  },
  {
    "name": "Kobayashi",
    "value": 80000,
    "gender": "Mujer",
    "source": "Kobayashi-san Chi no Dragon Maid",
    "keyword": "kobayashi"
  },
  {
    "name": "Conny",
    "value": 50000,
    "gender": "Mujer",
    "source": "Miira no Kaikata",
    "keyword": "coony_(miira_no_kaikata)"
  },
  {
    "name": "Jotaro Kujo",
    "value": 600000,
    "gender": "Hombre",
    "source": "JoJo's Bizarre Adventure",
    "keyword": "jotaro_kujo"
  },
  {
    "name": "Star Platinum",
    "value": 300000,
    "gender": "Hombre",
    "source": "JoJo's Bizarre Adventure",
    "keyword": "star_platinum"
  },
  {
    "name": "Giorno Giovanna",
    "value": 400000,
    "gender": "Hombre",
    "source": "JoJo's Bizarre Adventure",
    "keyword": "giorno_giovanna"
  },
  {
    "name": "Kishibe Rohan",
    "value": 200000,
    "gender": "Hombre",
    "source": "JoJo's Bizarre Adventure",
    "keyword": "kishibe_rohan"
  },
  {
    "name": "The World",
    "value": 161694,
    "gender": "Hombre",
    "source": "JoJo's Bizarre Adventure",
    "keyword": "the_world"
  },
  {
    "name": "Nakano Ichika",
    "value": 80000,
    "gender": "Mujer",
    "source": "Gotoubun no Hanayome",
    "keyword": "nakano_ichika"
  },
  {
    "name": "Nakano Yotsuba",
    "value": 144023,
    "gender": "Mujer",
    "source": "Gotoubun no Hanayome",
    "keyword": "nakano_yotsuba"
  },
  {
    "name": "Nakano Itsuki",
    "value": 80000,
    "gender": "Mujer",
    "source": "Gotoubun no Hanayome",
    "keyword": "nakano_itsuki"
  },
  {
    "name": "Uesugi Fuutarou",
    "value": 80000,
    "gender": "Hombre",
    "source": "Gotoubun no Hanayome",
    "keyword": "uesugi_fuutarou"
  },
  {
    "name": "Ichika",
    "value": 98899,
    "gender": "Mujer",
    "source": "Blue Archive",
    "keyword": "ichika_(blue_archive)"
  },
  {
    "name": "Hina",
    "value": 286965,
    "gender": "Mujer",
    "source": "Blue Archive",
    "keyword": "hina_(blue_archive)"
  },
  {
    "name": "Yuuka",
    "value": 134043,
    "gender": "Mujer",
    "source": "Blue Archive",
    "keyword": "yuuka_(blue_archive)"
  },
  {
    "name": "Tsukatsuki Rio",
    "value": 137870,
    "gender": "Mujer",
    "source": "Blue Archive",
    "keyword": "tsukatsuki_rio"
  },
  {
    "name": "Asuna",
    "value": 80000,
    "gender": "Mujer",
    "source": "Blue Archive",
    "keyword": "asuna_(blue_archive)"
  },
  {
    "name": "Karin",
    "value": 99291,
    "gender": "Mujer",
    "source": "Blue Archive",
    "keyword": "karin_(blue_archive)"
  },
  {
    "name": "Aris",
    "value": 80000,
    "gender": "Mujer",
    "source": "Blue Archive",
    "keyword": "aris_(blue_archive)"
  },
  {
    "name": "Kirino Nakatsukasa",
    "value": 169025,
    "gender": "Mujer",
    "source": "Blue Archive",
    "keyword": "kirino_(blue_archive)"
  },
  {
    "name": "Shiroko",
    "value": 80000,
    "gender": "Mujer",
    "source": "Blue Archive",
    "keyword": "shiroko_(blue_archive)"
  },
  {
    "name": "Aru",
    "value": 102826,
    "gender": "Mujer",
    "source": "Blue Archive",
    "keyword": "aru_(blue_archive)"
  },
  {
    "name": "Ui",
    "value": 80000,
    "gender": "Mujer",
    "source": "Blue Archive",
    "keyword": "ui_(blue_archive)"
  },
  {
    "name": "Momoi",
    "value": 102088,
    "gender": "Mujer",
    "source": "Blue Archive",
    "keyword": "momoi_(blue_archive)"
  },
  {
    "name": "Kisaki",
    "value": 133938,
    "gender": "Mujer",
    "source": "Blue Archive",
    "keyword": "kisaki_(blue_archive)"
  },
  {
    "name": "Hasumi",
    "value": 80000,
    "gender": "Mujer",
    "source": "Blue Archive",
    "keyword": "hasumi_(blue_archive)"
  },
  {
    "name": "Shalltear Bloodfallen",
    "value": 300000,
    "gender": "Mujer",
    "source": "Overlord",
    "keyword": "shalltear_bloodfallen"
  },
  {
    "name": "Arona",
    "value": 102438,
    "gender": "Mujer",
    "source": "Blue Archive",
    "keyword": "arona_(blue_archive)"
  },
  {
    "name": "Onikata Kayoko",
    "value": 303201,
    "gender": "Mujer",
    "source": "Blue Archive",
    "keyword": "onikata_kayoko"
  },
  {
    "name": "Noa",
    "value": 80000,
    "gender": "Mujer",
    "source": "Blue Archive",
    "keyword": "noa_(blue_archive)"
  },
  {
    "name": "Nonomi",
    "value": 102224,
    "gender": "Mujer",
    "source": "Blue Archive",
    "keyword": "nonomi_(blue_archive)"
  },
  {
    "name": "Asuma Toki",
    "value": 80000,
    "gender": "Mujer",
    "source": "Blue Archive",
    "keyword": "asuma_toki"
  },
  {
    "name": "Saori",
    "value": 226898,
    "gender": "Mujer",
    "source": "Blue Archive",
    "keyword": "saori_(blue_archive)"
  },
  {
    "name": "Nozomi Tachibana",
    "value": 125390,
    "gender": "Mujer",
    "source": "Blue Archive",
    "keyword": "nozomi_(blue_archive)"
  },
  {
    "name": "Hikari Tachibana",
    "value": 204393,
    "gender": "Mujer",
    "source": "Blue Archive",
    "keyword": "hikari_(blue_archive)"
  },
  {
    "name": "Neru",
    "value": 279391,
    "gender": "Mujer",
    "source": "Blue Archive",
    "keyword": "neru_(blue_archive)"
  },
  {
    "name": "Yurizono Seia",
    "value": 204036,
    "gender": "Mujer",
    "source": "Blue Archive",
    "keyword": "yurizono_seia"
  },
  {
    "name": "Plana",
    "value": 169039,
    "gender": "Mujer",
    "source": "Blue Archive",
    "keyword": "plana_(blue_archive)"
  },
  {
    "name": "Fuuka",
    "value": 80000,
    "gender": "Mujer",
    "source": "Blue Archive",
    "keyword": "fuuka_(blue_archive)"
  },
  {
    "name": "Mutsuki",
    "value": 273973,
    "gender": "Mujer",
    "source": "Blue Archive",
    "keyword": "mutsuki_(blue_archive)"
  },
  {
    "name": "Akane",
    "value": 167394,
    "gender": "Mujer",
    "source": "Blue Archive",
    "keyword": "akane_(blue_archive)"
  },
  {
    "name": "Mari",
    "value": 80000,
    "gender": "Mujer",
    "source": "Blue Archive",
    "keyword": "mari_(blue_archive)"
  },
  {
    "name": "Serika",
    "value": 170761,
    "gender": "Mujer",
    "source": "Blue Archive",
    "keyword": "serika_(blue_archive)"
  },
  {
    "name": "Shimiko Endo",
    "value": 173838,
    "gender": "Mujer",
    "source": "Blue Archive",
    "keyword": "shimiko_(blue_archive)"
  },
  {
    "name": "Nanagami Rin",
    "value": 204393,
    "gender": "Mujer",
    "source": "Blue Archive",
    "keyword": "nanagami_rin"
  },
  {
    "name": "Hanazono Hakari",
    "value": 158916,
    "gender": "Mujer",
    "source": "Kimi no Koto ga Daidaidaidaidaisuki na 100-nin no Kanojo",
    "keyword": "hanazono_hakari"
  },
  {
    "name": "Yoshimoto Shizuka",
    "value": 189188,
    "gender": "Mujer",
    "source": "Kimi no Koto ga Daidaidaidaidaisuki na 100-nin no Kanojo",
    "keyword": "yoshimoto_shizuka"
  },
  {
    "name": "Inda Karane",
    "value": 215956,
    "gender": "Mujer",
    "source": "Kimi no Koto ga Daidaidaidaidaisuki na 100-nin no Kanojo",
    "keyword": "inda_karane"
  },
  {
    "name": "Kagamine Rin",
    "value": 189390,
    "gender": "Mujer",
    "source": "Vocaloid",
    "keyword": "kagamine_rin"
  },
  {
    "name": "Kaito",
    "value": 396885,
    "gender": "Hombre",
    "source": "Vocaloid",
    "keyword": "kaito_(vocaloid)"
  },
  {
    "name": "Megurine Luka",
    "value": 184390,
    "gender": "Mujer",
    "source": "Vocaloid",
    "keyword": "megurine_luka"
  },
  {
    "name": "Akita Neru",
    "value": 80000,
    "gender": "Mujer",
    "source": "Vocaloid",
    "keyword": "akita_neru"
  },
  {
    "name": "Kagamine Len",
    "value": 80000,
    "gender": "Hombre",
    "source": "Vocaloid",
    "keyword": "kagamine_len"
  },
  {
    "name": "Oliver",
    "value": 80000,
    "gender": "Hombre",
    "source": "Vocaloid",
    "keyword": "oliver_(vocaloid)"
  },
  {
    "name": "Flower",
    "value": 192485,
    "gender": "Mujer",
    "source": "Vocaloid",
    "keyword": "flower_(vocaloid)"
  },
  {
    "name": "Gumi",
    "value": 80000,
    "gender": "Mujer",
    "source": "Vocaloid",
    "keyword": "gumi"
  },
  {
    "name": "Waguri Kaoruko",
    "value": 30000,
    "gender": "Mujer",
    "source": "Kaoru Hana wa Rin to Saku",
    "keyword": "waguri_kaoruko"
  },
  {
    "name": "Hoshina Subaru",
    "value": 30000,
    "gender": "Mujer",
    "source": "Kaoru Hana wa Rin to Saku",
    "keyword": "hoshina_subaru"
  },
  {
    "name": "Tsumugi Rintarou",
    "value": 30000,
    "gender": "Hombre",
    "source": "Kaoru Hana wa Rin to Saku",
    "keyword": "tsumugi_rintarou"
  },
  {
    "name": "Yuzuhara Madoka",
    "value": 30000,
    "gender": "Mujer",
    "source": "Kaoru Hana wa Rin to Saku",
    "keyword": "yuzuhara_madoka"
  },
  {
    "name": "Natsusawa Saku",
    "value": 30000,
    "gender": "Hombre",
    "source": "Kaoru Hana wa Rin to Saku",
    "keyword": "natsusawa_saku"
  },
  {
    "name": "Usami Shouhei",
    "value": 30000,
    "gender": "Hombre",
    "source": "Kaoru Hana wa Rin to Saku",
    "keyword": "usami_shouhei"
  },
  {
    "name": "Yorita Ayato",
    "value": 30000,
    "gender": "Hombre",
    "source": "Kaoru Hana wa Rin to Saku",
    "keyword": "yorita_ayato"
  },
  {
    "name": "Zenin Mai",
    "value": 296190,
    "gender": "Mujer",
    "source": "Jujutsu Kaisen",
    "keyword": "zenin_mai"
  },
  {
    "name": "Miwa Kasumi",
    "value": 150000,
    "gender": "Mujer",
    "source": "Jujutsu Kaisen",
    "keyword": "miwa_kasumi"
  },
  {
    "name": "Choso",
    "value": 350000,
    "gender": "Hombre",
    "source": "Jujutsu Kaisen",
    "keyword": "choso_(jujutsu_kaisen)"
  },
  {
    "name": "Zenin Maki",
    "value": 965600,
    "gender": "Mujer",
    "source": "Jujutsu Kaisen",
    "keyword": "zenin_maki"
  },
  {
    "name": "Mei Mei",
    "value": 300000,
    "gender": "Mujer",
    "source": "Jujutsu Kaisen",
    "keyword": "mei_mei_(jujutsu_kaisen)"
  },
  {
    "name": "Fushiguro Megumi",
    "value": 863860,
    "gender": "Hombre",
    "source": "Jujutsu Kaisen",
    "keyword": "fushiguro_megumi"
  },
  {
    "name": "Kugisaki Nobara",
    "value": 500000,
    "gender": "Mujer",
    "source": "Jujutsu Kaisen",
    "keyword": "kugisaki_nobara"
  },
  {
    "name": "Yusepe",
    "value": 309768,
    "gender": "Desconocido",
    "source": "Jujutsu Kaisen",
    "keyword": "yusepe_(jujutsu_kaisen)"
  },
  {
    "name": "Nanami Kento",
    "value": 400000,
    "gender": "Hombre",
    "source": "Jujutsu Kaisen",
    "keyword": "nanami_kento"
  },
  {
    "name": "Mahito",
    "value": 583670,
    "gender": "Hombre",
    "source": "Jujutsu Kaisen",
    "keyword": "mahito_(jujutsu_kaisen)"
  },
  {
    "name": "Ram",
    "value": 200000,
    "gender": "Mujer",
    "source": "Re:Zero",
    "keyword": "ram_(re:zero)"
  },
  {
    "name": "Pack",
    "value": 150000,
    "gender": "Desconocido",
    "source": "Re:Zero",
    "keyword": "pack_(re:zero)"
  },
  {
    "name": "Beatrice",
    "value": 376680,
    "gender": "Mujer",
    "source": "Re:Zero",
    "keyword": "beatrice_(re:zero)"
  },
  {
    "name": "Subaru Natsuki",
    "value": 300000,
    "gender": "Hombre",
    "source": "Re:Zero",
    "keyword": "subaru_natsuki_(re:zero)"
  },
  {
    "name": "Satella",
    "value": 350000,
    "gender": "Mujer",
    "source": "Re:Zero",
    "keyword": "satella_(re:zero)"
  },
  {
    "name": "Shalltear Bloodfallen",
    "value": 300000,
    "gender": "Mujer",
    "source": "Overlord",
    "keyword": "shalltear_bloodfallen"
  },
  {
    "name": "Sailor Moon",
    "value": 500000,
    "gender": "Mujer",
    "source": "Sailor Moon",
    "keyword": "sailor_moon"
  },
  {
    "name": "Nami",
    "value": 829000,
    "gender": "Mujer",
    "source": "One Piece",
    "keyword": "nami"
  },
  {
    "name": "Uta",
    "value": 968900,
    "gender": "Mujer",
    "source": "One Piece",
    "keyword": "uta"
  },
  {
    "name": "Perona",
    "value": 327290,
    "gender": "Mujer",
    "source": "One Piece",
    "keyword": "perona"
  },
  {
    "name": "Sailor Venus",
    "value": 210474,
    "gender": "Mujer",
    "source": "Sailor Moon",
    "keyword": "sailor_venus"
  },
  {
    "name": "Sailor Mars",
    "value": 155644,
    "gender": "Mujer",
    "source": "Sailor Moon",
    "keyword": "sailor_mars"
  },
  {
    "name": "Sailor Mercury",
    "value": 120000,
    "gender": "Mujer",
    "source": "Sailor Moon",
    "keyword": "sailor_mercury"
  },
  {
    "name": "Kanna Kamui",
    "value": 300000,
    "gender": "Mujer",
    "source": "Kobayashi-san Chi no Dragon Maid",
    "keyword": "kanna_kamui"
  },
  {
    "name": "Elma",
    "value": 80000,
    "gender": "Mujer",
    "source": "Kobayashi-san Chi no Dragon Maid",
    "keyword": "elma"
  },
  {
    "name": "Ilulu",
    "value": 80000,
    "gender": "Mujer",
    "source": "Kobayashi-san Chi no Dragon Maid",
    "keyword": "ilulu"
  },
  {
    "name": "Quetzalcoatl",
    "value": 80000,
    "gender": "Mujer",
    "source": "Kobayashi-san Chi no Dragon Maid",
    "keyword": "quetzalcoatl"
  },
  {
    "name": "Tohru",
    "value": 250000,
    "gender": "Mujer",
    "source": "Kobayashi-san Chi no Dragon Maid",
    "keyword": "tohru"
  },
  {
    "name": "Jolyne Kujo",
    "value": 400000,
    "gender": "Mujer",
    "source": "JoJo's Bizarre Adventure",
    "keyword": "jolyne_kujo"
  },
  {
    "name": "Dio Brando",
    "value": 500000,
    "gender": "Hombre",
    "source": "JoJo's Bizarre Adventure",
    "keyword": "dio_brando"
  },
  {
    "name": "Bruno Bucciarati ",
    "value": 100000,
    "gender": "Hombre",
    "source": "JoJo's Bizarre Adventure",
    "keyword": "bruno_bucciarati "
  },
  {
    "name": "Yamada Ryo",
    "value": 100000,
    "gender": "Mujer",
    "source": "Bocchi The Rock",
    "keyword": "yamada_ryo"
  },
  {
    "name": "Ijichi Nijika",
    "value": 80000,
    "gender": "Mujer",
    "source": "Bocchi The Rock",
    "keyword": "ijichi_nijika"
  },
  {
    "name": "Hiroi Kikuri",
    "value": 80000,
    "gender": "Mujer",
    "source": "Bocchi The Rock",
    "keyword": "hiroi_kikuri"
  },
  {
    "name": "Ijichi Seika",
    "value": 80000,
    "gender": "Mujer",
    "source": "Bocchi The Rock",
    "keyword": "ijichi_seika"
  },
  {
    "name": "Alisa Mikhailovna Kujou",
    "value": 180000,
    "gender": "Mujer",
    "source": "Tokidoki Bosotto Russia-go de Dereru Tonari no Alya-san",
    "keyword": "alisa_mikhailovna_kujou"
  },
  {
    "name": "Mariya Mikhailovna Kujou",
    "value": 128565,
    "gender": "Mujer",
    "source": "Tokidoki Bosotto Russia-go de Dereru Tonari no Alya-san",
    "keyword": "mariya_mikhailovna_kujou"
  },
  {
    "name": "Kimishima Ayano",
    "value": 128565,
    "gender": "Mujer",
    "source": "Tokidoki Bosotto Russia-go de Dereru Tonari no Alya-san",
    "keyword": "kimishima_ayano"
  },
  {
    "name": "Retzel",
    "value": 138600,
    "gender": "Mujer",
    "source": "Prima Doll",
    "keyword": "retzel_(prima_doll)"
  },
  {
    "name": "Haizakura",
    "value": 138600,
    "gender": "Mujer",
    "source": "Prima Doll",
    "keyword": "haizakura_(prima_doll)"
  },
  {
    "name": "Karasuba",
    "value": 60885,
    "gender": "Mujer",
    "source": "Prima Doll",
    "keyword": "karasuba_(prima_doll)"
  },
  {
    "name": "Gekka",
    "value": 138600,
    "gender": "Mujer",
    "source": "Prima Doll",
    "keyword": "gekka_(prima_doll)"
  },
  {
    "name": "Varesa",
    "value": 158400,
    "gender": "Mujer",
    "source": "Genshin Impact",
    "keyword": "varesa_(genshin_impact)"
  },
  {
    "name": "Reze",
    "value": 350000,
    "gender": "Mujer",
    "source": "Chainsaw Man",
    "keyword": "reze_(chainsaw_man)"
  },
  {
    "name": "Himeno",
    "value": 300000,
    "gender": "Mujer",
    "source": "Chainsaw Man",
    "keyword": "himeno_(chainsaw_man)"
  },
  {
    "name": "Angel Devil",
    "value": 200000,
    "gender": "Hombre",
    "source": "Chainsaw Man",
    "keyword": "angel_devil_(chainsaw_man)"
  },
  {
    "name": "Wiz",
    "value": 200000,
    "gender": "Mujer",
    "source": "Kono Subarashii Sekai ni Shukufuku wo!",
    "keyword": "wiz_(konosuba)"
  },
  {
    "name": "Lucoa",
    "value": 218080,
    "gender": "Mujer",
    "source": "Kono Subarashii Sekai ni Shukufuku wo!",
    "keyword": "megumin"
  },
  {
    "name": "Yunyun",
    "value": 180000,
    "gender": "Mujer",
    "source": "Kono Subarashii Sekai ni Shukufuku wo!",
    "keyword": "yunyun_(konosuba)"
  },
  {
    "name": "Aqua",
    "value": 250000,
    "gender": "Mujer",
    "source": "Kono Subarashii Sekai ni Shukufuku wo!",
    "keyword": "aqua_(konosuba)"
  },
  {
    "name": "Mita",
    "value": 180000,
    "gender": "Mujer",
    "source": "MiSide",
    "keyword": "mita_(miside)"
  },
  {
    "name": "Cool Mita",
    "value": 200000,
    "gender": "Mujer",
    "source": "MiSide",
    "keyword": "cool_mita_(miside)"
  },
  {
    "name": "Chara",
    "value": 250000,
    "gender": "Desconocido",
    "source": "Undertale",
    "keyword": "chara"
  },
  {
    "name": "Katayama Kumi",
    "value": 50000,
    "gender": "Mujer",
    "source": "Persona",
    "keyword": "katayama_kumi"
  },
  {
    "name": "Hatsune Miku",
    "value": 400000,
    "gender": "Mujer",
    "source": "Vocaloid",
    "keyword": "hatsune_miku"
  },
  {
    "name": "Sakurasawa Sumi",
    "value": 30000,
    "gender": "Mujer",
    "source": "Kanojo, Okarishimasu",
    "keyword": "sakurasawa_sumi"
  },
  {
    "name": "Hoshino Aquamarine",
    "value": 500000,
    "gender": "Hombre",
    "source": "Oshi no Ko",
    "keyword": "hoshino_aquamarine"
  },
  {
    "name": "Hoshino Ruby",
    "value": 400000,
    "gender": "Mujer",
    "source": "Oshi no Ko",
    "keyword": "hoshino_ruby"
  },
  {
    "name": "Arima Kana",
    "value": 250000,
    "gender": "Mujer",
    "source": "Oshi no Ko",
    "keyword": "arima_kana"
  },
  {
    "name": "Kurokawa Akane",
    "value": 300000,
    "gender": "Mujer",
    "source": "Oshi no Ko",
    "keyword": "kurokawa_akane"
  },
  {
    "name": "Mem-Cho",
    "value": 200000,
    "gender": "Mujer",
    "source": "Oshi no Ko",
    "keyword": "mem-cho"
  },
  {
    "name": "Amamiya Gorou",
    "value": 50000,
    "gender": "Hombre",
    "source": "Oshi no Ko",
    "keyword": "amamiya_gorou"
  },
  {
    "name": "Shiranui Frill",
    "value": 50000,
    "gender": "Mujer",
    "source": "Oshi no Ko",
    "keyword": "shiranui_frill"
  },
  {
    "name": "Saitou Miyako",
    "value": 50000,
    "gender": "Mujer",
    "source": "Oshi no Ko",
    "keyword": "saitou_miyako"
  },
  {
    "name": "Saitou Ichigo",
    "value": 50000,
    "gender": "Hombre",
    "source": "Oshi no Ko",
    "keyword": "saitou_ichigo"
  },
  {
    "name": "Chocola",
    "value": 40000,
    "gender": "Mujer",
    "source": "Nekopara",
    "keyword": "chocola"
  },
  {
    "name": "Vanilla",
    "value": 40000,
    "gender": "Mujer",
    "source": "Nekopara",
    "keyword": "vanilla"
  },
  {
    "name": "Cinnamon",
    "value": 40000,
    "gender": "Mujer",
    "source": "Nekopara",
    "keyword": "cinnamon_(nekopara) "
  },
  {
    "name": "Coconut",
    "value": 40000,
    "gender": "Mujer",
    "source": "Nekopara",
    "keyword": "coconut_(nekopara) "
  },
  {
    "name": "Maple",
    "value": 40000,
    "gender": "Mujer",
    "source": "Nekopara",
    "keyword": "maple_(nekopara)"
  },
  {
    "name": "Cacao",
    "value": 40000,
    "gender": "Mujer",
    "source": "Nekopara",
    "keyword": "cacao_(nekopara) "
  },
  {
    "name": "Mizuhara Chizuru",
    "value": 30000,
    "gender": "Mujer",
    "source": "Kanojo, Okarishimasu",
    "keyword": "mizuhara_chizuru"
  },
  {
    "name": "Kinoshita Kazuya",
    "value": 30000,
    "gender": "Hombre",
    "source": "Kanojo, Okarishimasu",
    "keyword": "kinoshita_kazuya"
  },
  {
    "name": "Sarashina Ruka",
    "value": 30000,
    "gender": "Mujer",
    "source": "Kanojo, Okarishimasu",
    "keyword": "sarashina_ruka"
  },
  {
    "name": "Nanami Mami",
    "value": 30000,
    "gender": "Mujer",
    "source": "Kanojo, Okarishimasu",
    "keyword": "nanami_mami"
  },
  {
    "name": "Yaemori Mini",
    "value": 30000,
    "gender": "Mujer",
    "source": "Kanojo, Okarishimasu",
    "keyword": "yaemori_mini"
  },
  {
    "name": "Shiina Mahiru",
    "value": 60000,
    "gender": "Mujer",
    "source": "Otonari no Tenshi-sama ni Itsunomanika Dame Ningen ni Sareteita Ken",
    "keyword": "shiina_mahiru_(otonari_no_tenshi-sama)"
  },
  {
    "name": "Sylpha Langlis",
    "value": 50000,
    "gender": "Mujer",
    "source": "Tensei shitara Dainana Ouji Datta node, Kimama ni Majutsu wo Kiwamemasu",
    "keyword": "sylpha_(dai_nana_oji)"
  },
  {
    "name": "Tina Sprout",
    "value": 50000,
    "gender": "Mujer",
    "source": "Black Bullet",
    "keyword": "tina_sprout"
  },
  {
    "name": "Ahiara Enju",
    "value": 50000,
    "gender": "Mujer",
    "source": "Black Bullet",
    "keyword": "aihara_enju"
  },
  {
    "name": "Kubo Nagisa",
    "value": 50000,
    "gender": "Mujer",
    "source": "Kubo-san wa Mob wo Yurusanai",
    "keyword": "kubo_nagisa"
  },
  {
    "name": "Latifa Fleuranza",
    "value": 50000,
    "gender": "Mujer",
    "source": "Amagami Brilliant Park",
    "keyword": "latifa_fleuranza"
  },
  {
    "name": "Konjiki No Yami",
    "value": 80000,
    "gender": "Mujer",
    "source": "To LOVE-Ru",
    "keyword": "konjiki_no_yami"
  },
  {
    "name": "Tanjiro Kamado",
    "value": 2500000,
    "gender": "Hombre",
    "source": "Demon Slayer",
    "keyword": "tanjiro_kamado"
  },
  {
    "name": "Nezuko Kamado",
    "value": 3500000,
    "gender": "Mujer",
    "source": "Demon Slayer",
    "keyword": "nezuko_kamado"
  },
  {
    "name": "Zenitsu Agatsuma",
    "value": 1800000,
    "gender": "Hombre",
    "source": "Demon Slayer",
    "keyword": "zenitsu_agatsuma"
  },
  {
    "name": "Inosuke Hashibira",
    "value": 1500000,
    "gender": "Hombre",
    "source": "Demon Slayer",
    "keyword": "inosuke_hashibira"
  },
  {
    "name": "Kyojuro Rengoku",
    "value": 3000000,
    "gender": "Hombre",
    "source": "Demon Slayer",
    "keyword": "kyojuro_rengoku"
  },
  {
    "name": "Giyu Tomioka",
    "value": 2200000,
    "gender": "Hombre",
    "source": "Demon Slayer",
    "keyword": "giyu_tomioka"
  },
  {
    "name": "Shinobu Kocho",
    "value": 2800000,
    "gender": "Mujer",
    "source": "Demon Slayer",
    "keyword": "shinobu_kocho"
  },
  {
    "name": "Mitsuri Kanroji",
    "value": 2500000,
    "gender": "Mujer",
    "source": "Demon Slayer",
    "keyword": "mitsuri_kanroji"
  },
  {
    "name": "Muzan Kibutsuji",
    "value": 2000000,
    "gender": "Hombre",
    "source": "Demon Slayer",
    "keyword": "muzan_kibutsuji"
  },
  {
    "name": "Kanao Tsuyuri",
    "value": 1800000,
    "gender": "Mujer",
    "source": "Demon Slayer",
    "keyword": "kanao_tsuyuri"
  },
  {
    "name": "Muichiro Tokito",
    "value": 1600000,
    "gender": "Hombre",
    "source": "Demon Slayer",
    "keyword": "muichiro_tokito"
  },
  {
    "name": "Tengen Uzui",
    "value": 1400000,
    "gender": "Hombre",
    "source": "Demon Slayer",
    "keyword": "tengen_uzui"
  },
  {
    "name": "Eren Yeager",
    "value": 3000000,
    "gender": "Hombre",
    "source": "Attack on Titan",
    "keyword": "eren_yeager"
  },
  {
    "name": "Mikasa Ackerman",
    "value": 3500000,
    "gender": "Mujer",
    "source": "Attack on Titan",
    "keyword": "mikasa_ackerman"
  },
  {
    "name": "Levi Ackerman",
    "value": 5000000,
    "gender": "Hombre",
    "source": "Attack on Titan",
    "keyword": "levi_ackerman"
  },
  {
    "name": "Historia Reiss",
    "value": 2000000,
    "gender": "Mujer",
    "source": "Attack on Titan",
    "keyword": "historia_reiss"
  },
  {
    "name": "Armin Arlert",
    "value": 1500000,
    "gender": "Hombre",
    "source": "Attack on Titan",
    "keyword": "armin_arlert"
  },
  {
    "name": "Erwin Smith",
    "value": 2500000,
    "gender": "Hombre",
    "source": "Attack on Titan",
    "keyword": "erwin_smith"
  },
  {
    "name": "Hange Zoe",
    "value": 1800000,
    "gender": "Mujer",
    "source": "Attack on Titan",
    "keyword": "hange_zoe"
  },
  {
    "name": "Annie Leonhart",
    "value": 2200000,
    "gender": "Mujer",
    "source": "Attack on Titan",
    "keyword": "annie_leonhart"
  },
  {
    "name": "Reiner Braun",
    "value": 1200000,
    "gender": "Hombre",
    "source": "Attack on Titan",
    "keyword": "reiner_braun"
  },
  {
    "name": "Sasha Braus",
    "value": 1500000,
    "gender": "Mujer",
    "source": "Attack on Titan",
    "keyword": "sasha_braus"
  },
  {
    "name": "Izuku Midoriya",
    "value": 2500000,
    "gender": "Hombre",
    "source": "My Hero Academia",
    "keyword": "izuku_midoriya"
  },
  {
    "name": "Katsuki Bakugo",
    "value": 2800000,
    "gender": "Hombre",
    "source": "My Hero Academia",
    "keyword": "katsuki_bakugo"
  },
  {
    "name": "Shoto Todoroki",
    "value": 2500000,
    "gender": "Hombre",
    "source": "My Hero Academia",
    "keyword": "shoto_todoroki"
  },
  {
    "name": "Ochaco Uraraka",
    "value": 2000000,
    "gender": "Mujer",
    "source": "My Hero Academia",
    "keyword": "ochaco_uraraka"
  },
  {
    "name": "All Might",
    "value": 3500000,
    "gender": "Hombre",
    "source": "My Hero Academia",
    "keyword": "all_might"
  },
  {
    "name": "Tsuyu Asui",
    "value": 1500000,
    "gender": "Mujer",
    "source": "My Hero Academia",
    "keyword": "tsuyu_asui"
  },
  {
    "name": "Momo Yaoyorozu",
    "value": 1800000,
    "gender": "Mujer",
    "source": "My Hero Academia",
    "keyword": "momo_yaoyorozu"
  },
  {
    "name": "Himiko Toga",
    "value": 2200000,
    "gender": "Mujer",
    "source": "My Hero Academia",
    "keyword": "himiko_toga"
  },
  {
    "name": "Dabi",
    "value": 1800000,
    "gender": "Hombre",
    "source": "My Hero Academia",
    "keyword": "dabi"
  },
  {
    "name": "Hawks",
    "value": 2500000,
    "gender": "Hombre",
    "source": "My Hero Academia",
    "keyword": "hawks"
  },
  {
    "name": "Sung Jinwoo",
    "value": 4500000,
    "gender": "Hombre",
    "source": "Solo Leveling",
    "keyword": "sung_jinwoo"
  },
  {
    "name": "Cha Hae-In",
    "value": 3500000,
    "gender": "Mujer",
    "source": "Solo Leveling",
    "keyword": "cha_hae-in"
  },
  {
    "name": "Yoo Jinho",
    "value": 800000,
    "gender": "Hombre",
    "source": "Solo Leveling",
    "keyword": "yoo_jinho"
  },
  {
    "name": "Go Gunhee",
    "value": 1200000,
    "gender": "Hombre",
    "source": "Solo Leveling",
    "keyword": "go_gunhee"
  },
  {
    "name": "Choi Jong-In",
    "value": 1000000,
    "gender": "Hombre",
    "source": "Solo Leveling",
    "keyword": "choi_jong-in"
  },
  {
    "name": "Okarun",
    "value": 2500000,
    "gender": "Hombre",
    "source": "Dandadan",
    "keyword": "okarun"
  },
  {
    "name": "Momo Ayase",
    "value": 3000000,
    "gender": "Mujer",
    "source": "Dandadan",
    "keyword": "momo_ayase"
  },
  {
    "name": "Aira Shiratori",
    "value": 1800000,
    "gender": "Mujer",
    "source": "Dandadan",
    "keyword": "aira_shiratori"
  },
  {
    "name": "Jiji",
    "value": 1500000,
    "gender": "Hombre",
    "source": "Dandadan",
    "keyword": "jiji_dandadan"
  },
  {
    "name": "Ken Kaneki",
    "value": 3500000,
    "gender": "Hombre",
    "source": "Tokyo Ghoul",
    "keyword": "ken_kaneki"
  },
  {
    "name": "Touka Kirishima",
    "value": 2800000,
    "gender": "Mujer",
    "source": "Tokyo Ghoul",
    "keyword": "touka_kirishima"
  },
  {
    "name": "Rize Kamishiro",
    "value": 1800000,
    "gender": "Mujer",
    "source": "Tokyo Ghoul",
    "keyword": "rize_kamishiro"
  },
  {
    "name": "Shuu Tsukiyama",
    "value": 1200000,
    "gender": "Hombre",
    "source": "Tokyo Ghoul",
    "keyword": "shuu_tsukiyama"
  },
  {
    "name": "Hideyoshi Nagachika",
    "value": 1000000,
    "gender": "Hombre",
    "source": "Tokyo Ghoul",
    "keyword": "hideyoshi_nagachika"
  },
  {
    "name": "Light Yagami",
    "value": 4000000,
    "gender": "Hombre",
    "source": "Death Note",
    "keyword": "light_yagami"
  },
  {
    "name": "L Lawliet",
    "value": 4500000,
    "gender": "Hombre",
    "source": "Death Note",
    "keyword": "l_lawliet"
  },
  {
    "name": "Misa Amane",
    "value": 2500000,
    "gender": "Mujer",
    "source": "Death Note",
    "keyword": "misa_amane"
  },
  {
    "name": "Near",
    "value": 1500000,
    "gender": "Hombre",
    "source": "Death Note",
    "keyword": "near_death_note"
  },
  {
    "name": "Ryuk",
    "value": 2000000,
    "gender": "Hombre",
    "source": "Death Note",
    "keyword": "ryuk"
  },
  {
    "name": "Edward Elric",
    "value": 3500000,
    "gender": "Hombre",
    "source": "Fullmetal Alchemist",
    "keyword": "edward_elric"
  },
  {
    "name": "Alphonse Elric",
    "value": 2500000,
    "gender": "Hombre",
    "source": "Fullmetal Alchemist",
    "keyword": "alphonse_elric"
  },
  {
    "name": "Roy Mustang",
    "value": 3000000,
    "gender": "Hombre",
    "source": "Fullmetal Alchemist",
    "keyword": "roy_mustang"
  },
  {
    "name": "Riza Hawkeye",
    "value": 2200000,
    "gender": "Mujer",
    "source": "Fullmetal Alchemist",
    "keyword": "riza_hawkeye"
  },
  {
    "name": "Winry Rockbell",
    "value": 1800000,
    "gender": "Mujer",
    "source": "Fullmetal Alchemist",
    "keyword": "winry_rockbell"
  },
  {
    "name": "Kirito",
    "value": 3000000,
    "gender": "Hombre",
    "source": "Sword Art Online",
    "keyword": "kirito"
  },
  {
    "name": "Asuna Yuuki",
    "value": 3500000,
    "gender": "Mujer",
    "source": "Sword Art Online",
    "keyword": "asuna_yuuki"
  },
  {
    "name": "Sinon",
    "value": 2000000,
    "gender": "Mujer",
    "source": "Sword Art Online",
    "keyword": "sinon"
  },
  {
    "name": "Leafa",
    "value": 1500000,
    "gender": "Mujer",
    "source": "Sword Art Online",
    "keyword": "leafa"
  },
  {
    "name": "Alice Zuberg",
    "value": 2500000,
    "gender": "Mujer",
    "source": "Sword Art Online",
    "keyword": "alice_zuberg"
  },
  {
    "name": "Saber",
    "value": 4000000,
    "gender": "Mujer",
    "source": "Fate",
    "keyword": "saber_fate"
  },
  {
    "name": "Rin Tohsaka",
    "value": 3000000,
    "gender": "Mujer",
    "source": "Fate",
    "keyword": "rin_tohsaka"
  },
  {
    "name": "Shirou Emiya",
    "value": 2000000,
    "gender": "Hombre",
    "source": "Fate",
    "keyword": "shirou_emiya"
  },
  {
    "name": "Gilgamesh",
    "value": 3500000,
    "gender": "Hombre",
    "source": "Fate",
    "keyword": "gilgamesh_fate"
  },
  {
    "name": "Sakura Matou",
    "value": 2200000,
    "gender": "Mujer",
    "source": "Fate",
    "keyword": "sakura_matou"
  },
  {
    "name": "Rider Medusa",
    "value": 1800000,
    "gender": "Mujer",
    "source": "Fate",
    "keyword": "rider_medusa"
  },
  {
    "name": "Shinji Ikari",
    "value": 2000000,
    "gender": "Hombre",
    "source": "Evangelion",
    "keyword": "shinji_ikari"
  },
  {
    "name": "Rei Ayanami",
    "value": 3500000,
    "gender": "Mujer",
    "source": "Evangelion",
    "keyword": "rei_ayanami"
  },
  {
    "name": "Asuka Langley",
    "value": 3500000,
    "gender": "Mujer",
    "source": "Evangelion",
    "keyword": "asuka_langley"
  },
  {
    "name": "Kaworu Nagisa",
    "value": 2000000,
    "gender": "Hombre",
    "source": "Evangelion",
    "keyword": "kaworu_nagisa"
  },
  {
    "name": "Misato Katsuragi",
    "value": 2500000,
    "gender": "Mujer",
    "source": "Evangelion",
    "keyword": "misato_katsuragi"
  },
  {
    "name": "Okabe Rintaro",
    "value": 2500000,
    "gender": "Hombre",
    "source": "Steins;Gate",
    "keyword": "okabe_rintaro"
  },
  {
    "name": "Kurisu Makise",
    "value": 3500000,
    "gender": "Mujer",
    "source": "Steins;Gate",
    "keyword": "kurisu_makise"
  },
  {
    "name": "Mayuri Shiina",
    "value": 2000000,
    "gender": "Mujer",
    "source": "Steins;Gate",
    "keyword": "mayuri_shiina"
  },
  {
    "name": "Suzuha Amane",
    "value": 1500000,
    "gender": "Mujer",
    "source": "Steins;Gate",
    "keyword": "suzuha_amane"
  },
  {
    "name": "Taiga Aisaka",
    "value": 3000000,
    "gender": "Mujer",
    "source": "Toradora",
    "keyword": "taiga_aisaka"
  },
  {
    "name": "Ryuuji Takasu",
    "value": 1500000,
    "gender": "Hombre",
    "source": "Toradora",
    "keyword": "ryuuji_takasu"
  },
  {
    "name": "Minori Kushieda",
    "value": 1800000,
    "gender": "Mujer",
    "source": "Toradora",
    "keyword": "minori_kushieda"
  },
  {
    "name": "Ami Kawashima",
    "value": 1500000,
    "gender": "Mujer",
    "source": "Toradora",
    "keyword": "ami_kawashima"
  },
  {
    "name": "Kousei Arima",
    "value": 2000000,
    "gender": "Hombre",
    "source": "Your Lie in April",
    "keyword": "kousei_arima"
  },
  {
    "name": "Kaori Miyazono",
    "value": 3500000,
    "gender": "Mujer",
    "source": "Your Lie in April",
    "keyword": "kaori_miyazono"
  },
  {
    "name": "Tsubaki Sawabe",
    "value": 1200000,
    "gender": "Mujer",
    "source": "Your Lie in April",
    "keyword": "tsubaki_sawabe"
  },
  {
    "name": "Chisato Nishikigi",
    "value": 3500000,
    "gender": "Mujer",
    "source": "Lycoris Recoil",
    "keyword": "chisato_nishikigi"
  },
  {
    "name": "Takina Inoue",
    "value": 3000000,
    "gender": "Mujer",
    "source": "Lycoris Recoil",
    "keyword": "takina_inoue"
  },
  {
    "name": "Kurumi Saiki",
    "value": 1200000,
    "gender": "Mujer",
    "source": "Lycoris Recoil",
    "keyword": "kurumi_saiki"
  },
  {
    "name": "Rudeus Greyrat",
    "value": 2500000,
    "gender": "Hombre",
    "source": "Mushoku Tensei",
    "keyword": "rudeus_greyrat"
  },
  {
    "name": "Eris Boreas Greyrat",
    "value": 3000000,
    "gender": "Mujer",
    "source": "Mushoku Tensei",
    "keyword": "eris_boreas_greyrat"
  },
  {
    "name": "Roxy Migurdia",
    "value": 3500000,
    "gender": "Mujer",
    "source": "Mushoku Tensei",
    "keyword": "roxy_migurdia"
  },
  {
    "name": "Sylphiette",
    "value": 2500000,
    "gender": "Mujer",
    "source": "Mushoku Tensei",
    "keyword": "sylphiette"
  },
  {
    "name": "Naofumi Iwatani",
    "value": 2000000,
    "gender": "Hombre",
    "source": "Shield Hero",
    "keyword": "naofumi_iwatani"
  },
  {
    "name": "Raphtalia",
    "value": 3500000,
    "gender": "Mujer",
    "source": "Shield Hero",
    "keyword": "raphtalia"
  },
  {
    "name": "Filo",
    "value": 1800000,
    "gender": "Mujer",
    "source": "Shield Hero",
    "keyword": "filo_shield_hero"
  },
  {
    "name": "Thorfinn",
    "value": 2500000,
    "gender": "Hombre",
    "source": "Vinland Saga",
    "keyword": "thorfinn"
  },
  {
    "name": "Askeladd",
    "value": 3000000,
    "gender": "Hombre",
    "source": "Vinland Saga",
    "keyword": "askeladd"
  },
  {
    "name": "Canute",
    "value": 2000000,
    "gender": "Hombre",
    "source": "Vinland Saga",
    "keyword": "canute_vinland"
  },
  {
    "name": "Thorkell",
    "value": 1500000,
    "gender": "Hombre",
    "source": "Vinland Saga",
    "keyword": "thorkell"
  },
  {
    "name": "Gon Freecss",
    "value": 2500000,
    "gender": "Hombre",
    "source": "Hunter x Hunter",
    "keyword": "gon_freecss"
  },
  {
    "name": "Killua Zoldyck",
    "value": 3500000,
    "gender": "Hombre",
    "source": "Hunter x Hunter",
    "keyword": "killua_zoldyck"
  },
  {
    "name": "Hisoka Morow",
    "value": 3000000,
    "gender": "Hombre",
    "source": "Hunter x Hunter",
    "keyword": "hisoka_morow"
  },
  {
    "name": "Kurapika",
    "value": 2800000,
    "gender": "Hombre",
    "source": "Hunter x Hunter",
    "keyword": "kurapika"
  },
  {
    "name": "Leorio Paradinight",
    "value": 1200000,
    "gender": "Hombre",
    "source": "Hunter x Hunter",
    "keyword": "leorio_paradinight"
  },
  {
    "name": "Shigeo Kageyama",
    "value": 2500000,
    "gender": "Hombre",
    "source": "Mob Psycho 100",
    "keyword": "shigeo_kageyama"
  },
  {
    "name": "Arataka Reigen",
    "value": 2000000,
    "gender": "Hombre",
    "source": "Mob Psycho 100",
    "keyword": "arataka_reigen"
  },
  {
    "name": "Teruki Hanazawa",
    "value": 1200000,
    "gender": "Hombre",
    "source": "Mob Psycho 100",
    "keyword": "teruki_hanazawa"
  },
  {
    "name": "Ritsu Kageyama",
    "value": 1000000,
    "gender": "Hombre",
    "source": "Mob Psycho 100",
    "keyword": "ritsu_kageyama"
  },
  {
    "name": "Asta",
    "value": 2500000,
    "gender": "Hombre",
    "source": "Black Clover",
    "keyword": "asta_black_clover"
  },
  {
    "name": "Yuno",
    "value": 2200000,
    "gender": "Hombre",
    "source": "Black Clover",
    "keyword": "yuno_black_clover"
  },
  {
    "name": "Noelle Silva",
    "value": 2800000,
    "gender": "Mujer",
    "source": "Black Clover",
    "keyword": "noelle_silva"
  },
  {
    "name": "Yami Sukehiro",
    "value": 2000000,
    "gender": "Hombre",
    "source": "Black Clover",
    "keyword": "yami_sukehiro"
  },
  {
    "name": "Mimosa Vermillion",
    "value": 1800000,
    "gender": "Mujer",
    "source": "Black Clover",
    "keyword": "mimosa_vermillion"
  },
  {
    "name": "Ichigo Kurosaki",
    "value": 3500000,
    "gender": "Hombre",
    "source": "Bleach",
    "keyword": "ichigo_kurosaki"
  },
  {
    "name": "Rukia Kuchiki",
    "value": 3000000,
    "gender": "Mujer",
    "source": "Bleach",
    "keyword": "rukia_kuchiki"
  },
  {
    "name": "Orihime Inoue",
    "value": 2200000,
    "gender": "Mujer",
    "source": "Bleach",
    "keyword": "orihime_inoue"
  },
  {
    "name": "Sosuke Aizen",
    "value": 3500000,
    "gender": "Hombre",
    "source": "Bleach",
    "keyword": "sosuke_aizen"
  },
  {
    "name": "Toshiro Hitsugaya",
    "value": 2500000,
    "gender": "Hombre",
    "source": "Bleach",
    "keyword": "toshiro_hitsugaya"
  },
  {
    "name": "Byakuya Kuchiki",
    "value": 2200000,
    "gender": "Hombre",
    "source": "Bleach",
    "keyword": "byakuya_kuchiki"
  },
  {
    "name": "Yoruichi Shihouin",
    "value": 2800000,
    "gender": "Mujer",
    "source": "Bleach",
    "keyword": "yoruichi_shihouin"
  },
  {
    "name": "Takemichi Hanagaki",
    "value": 1800000,
    "gender": "Hombre",
    "source": "Tokyo Revengers",
    "keyword": "takemichi_hanagaki"
  },
  {
    "name": "Manjiro Sano",
    "value": 3500000,
    "gender": "Hombre",
    "source": "Tokyo Revengers",
    "keyword": "manjiro_sano"
  },
  {
    "name": "Ken Ryuguji",
    "value": 2500000,
    "gender": "Hombre",
    "source": "Tokyo Revengers",
    "keyword": "ken_ryuguji"
  },
  {
    "name": "Hinata Tachibana",
    "value": 1500000,
    "gender": "Mujer",
    "source": "Tokyo Revengers",
    "keyword": "hinata_tachibana"
  },
  {
    "name": "Chifuyu Matsuno",
    "value": 1800000,
    "gender": "Hombre",
    "source": "Tokyo Revengers",
    "keyword": "chifuyu_matsuno"
  },
  {
    "name": "Shoyo Hinata",
    "value": 2200000,
    "gender": "Hombre",
    "source": "Haikyuu",
    "keyword": "shoyo_hinata"
  },
  {
    "name": "Tobio Kageyama",
    "value": 2200000,
    "gender": "Hombre",
    "source": "Haikyuu",
    "keyword": "tobio_kageyama"
  },
  {
    "name": "Kei Tsukishima",
    "value": 1500000,
    "gender": "Hombre",
    "source": "Haikyuu",
    "keyword": "kei_tsukishima"
  },
  {
    "name": "Tetsuro Kuroo",
    "value": 1800000,
    "gender": "Hombre",
    "source": "Haikyuu",
    "keyword": "tetsuro_kuroo"
  },
  {
    "name": "Kenma Kozume",
    "value": 2000000,
    "gender": "Hombre",
    "source": "Haikyuu",
    "keyword": "kenma_kozume"
  },
  {
    "name": "Koshi Sugawara",
    "value": 1200000,
    "gender": "Hombre",
    "source": "Haikyuu",
    "keyword": "koshi_sugawara"
  },
  {
    "name": "Shinra Kusakabe",
    "value": 2200000,
    "gender": "Hombre",
    "source": "Fire Force",
    "keyword": "shinra_kusakabe"
  },
  {
    "name": "Tamaki Kotatsu",
    "value": 2000000,
    "gender": "Mujer",
    "source": "Fire Force",
    "keyword": "tamaki_kotatsu"
  },
  {
    "name": "Maki Oze",
    "value": 2200000,
    "gender": "Mujer",
    "source": "Fire Force",
    "keyword": "maki_oze"
  },
  {
    "name": "Arthur Boyle",
    "value": 1500000,
    "gender": "Hombre",
    "source": "Fire Force",
    "keyword": "arthur_boyle"
  },
  {
    "name": "Natsu Dragneel",
    "value": 2500000,
    "gender": "Hombre",
    "source": "Fairy Tail",
    "keyword": "natsu_dragneel"
  },
  {
    "name": "Lucy Heartfilia",
    "value": 3000000,
    "gender": "Mujer",
    "source": "Fairy Tail",
    "keyword": "lucy_heartfilia"
  },
  {
    "name": "Erza Scarlet",
    "value": 3500000,
    "gender": "Mujer",
    "source": "Fairy Tail",
    "keyword": "erza_scarlet"
  },
  {
    "name": "Gray Fullbuster",
    "value": 2000000,
    "gender": "Hombre",
    "source": "Fairy Tail",
    "keyword": "gray_fullbuster"
  },
  {
    "name": "Juvia Lockser",
    "value": 2200000,
    "gender": "Mujer",
    "source": "Fairy Tail",
    "keyword": "juvia_lockser"
  },
  {
    "name": "Wendy Marvell",
    "value": 1800000,
    "gender": "Mujer",
    "source": "Fairy Tail",
    "keyword": "wendy_marvell"
  },
  {
    "name": "Denji",
    "value": 3000000,
    "gender": "Hombre",
    "source": "Chainsaw Man",
    "keyword": "denji"
  },
  {
    "name": "Makima",
    "value": 4000000,
    "gender": "Mujer",
    "source": "Chainsaw Man",
    "keyword": "makima"
  },
  {
    "name": "Power",
    "value": 3500000,
    "gender": "Mujer",
    "source": "Chainsaw Man",
    "keyword": "power_csm"
  },
  {
    "name": "Aki Hayakawa",
    "value": 2500000,
    "gender": "Hombre",
    "source": "Chainsaw Man",
    "keyword": "aki_hayakawa"
  },
  {
    "name": "Reze",
    "value": 2800000,
    "gender": "Mujer",
    "source": "Chainsaw Man",
    "keyword": "reze"
  },
  {
    "name": "Asa Mitaka",
    "value": 2500000,
    "gender": "Mujer",
    "source": "Chainsaw Man",
    "keyword": "asa_mitaka"
  },
  {
    "name": "Subaru Natsuki",
    "value": 1800000,
    "gender": "Hombre",
    "source": "Re:Zero",
    "keyword": "subaru_natsuki"
  },
  {
    "name": "Emilia",
    "value": 3500000,
    "gender": "Mujer",
    "source": "Re:Zero",
    "keyword": "emilia_rezero"
  },
  {
    "name": "Rem",
    "value": 4000000,
    "gender": "Mujer",
    "source": "Re:Zero",
    "keyword": "rem_rezero"
  },
  {
    "name": "Ram",
    "value": 2000000,
    "gender": "Mujer",
    "source": "Re:Zero",
    "keyword": "ram_rezero"
  },
  {
    "name": "Echidna",
    "value": 2500000,
    "gender": "Mujer",
    "source": "Re:Zero",
    "keyword": "echidna_rezero"
  },
  {
    "name": "Kazuma Sato",
    "value": 1500000,
    "gender": "Hombre",
    "source": "Konosuba",
    "keyword": "kazuma_sato"
  },
  {
    "name": "Aqua",
    "value": 3000000,
    "gender": "Mujer",
    "source": "Konosuba",
    "keyword": "aqua_konosuba"
  },
  {
    "name": "Megumin",
    "value": 4000000,
    "gender": "Mujer",
    "source": "Konosuba",
    "keyword": "megumin"
  },
  {
    "name": "Darkness",
    "value": 2500000,
    "gender": "Mujer",
    "source": "Konosuba",
    "keyword": "darkness_konosuba"
  },
  {
    "name": "Rimuru Tempest",
    "value": 3500000,
    "gender": "Hombre",
    "source": "Slime Isekai",
    "keyword": "rimuru_tempest"
  },
  {
    "name": "Shuna",
    "value": 2500000,
    "gender": "Mujer",
    "source": "Slime Isekai",
    "keyword": "shuna_slime"
  },
  {
    "name": "Shion",
    "value": 2200000,
    "gender": "Mujer",
    "source": "Slime Isekai",
    "keyword": "shion_slime"
  },
  {
    "name": "Milim Nava",
    "value": 3000000,
    "gender": "Mujer",
    "source": "Slime Isekai",
    "keyword": "milim_nava"
  },
  {
    "name": "Frieren",
    "value": 4500000,
    "gender": "Mujer",
    "source": "Frieren",
    "keyword": "frieren"
  },
  {
    "name": "Fern",
    "value": 3000000,
    "gender": "Mujer",
    "source": "Frieren",
    "keyword": "fern_frieren"
  },
  {
    "name": "Stark",
    "value": 2500000,
    "gender": "Hombre",
    "source": "Frieren",
    "keyword": "stark_frieren"
  },
  {
    "name": "Himmel",
    "value": 2000000,
    "gender": "Hombre",
    "source": "Frieren",
    "keyword": "himmel_frieren"
  },
  {
    "name": "Ubel",
    "value": 2800000,
    "gender": "Mujer",
    "source": "Frieren",
    "keyword": "ubel_frieren"
  }
]